odoo8_addon_l10n_fr_mis_reports-8.0.0.0.1.99.dev10-py2.7-nspkg.pth
odoo8_addon_l10n_fr_mis_reports-8.0.0.0.1.99.dev10.dist-info/METADATA
odoo8_addon_l10n_fr_mis_reports-8.0.0.0.1.99.dev10.dist-info/RECORD
odoo8_addon_l10n_fr_mis_reports-8.0.0.0.1.99.dev10.dist-info/WHEEL
odoo8_addon_l10n_fr_mis_reports-8.0.0.0.1.99.dev10.dist-info/namespace_packages.txt
odoo8_addon_l10n_fr_mis_reports-8.0.0.0.1.99.dev10.dist-info/top_level.txt
odoo_addons/l10n_fr_mis_reports/README.rst
odoo_addons/l10n_fr_mis_reports/__init__.py
odoo_addons/l10n_fr_mis_reports/__openerp__.py
odoo_addons/l10n_fr_mis_reports/data/mis_report_bs.xml
odoo_addons/l10n_fr_mis_reports/data/mis_report_bs_simplified.xml
odoo_addons/l10n_fr_mis_reports/data/mis_report_pl.xml
odoo_addons/l10n_fr_mis_reports/data/mis_report_pl_simplified.xml
odoo_addons/l10n_fr_mis_reports/i18n/it.po
odoo_addons/l10n_fr_mis_reports/i18n/l10n_fr_mis_reports.pot
odoo_addons/l10n_fr_mis_reports/static/description/icon.png
