Metadata-Version: 2.1
Name: odoo8-addon-l10n-fr-mis-reports
Version: 8.0.0.0.1.99.dev10
Summary: MIS Report templates for the French P&L and Balance Sheets
Home-page: http://www.akretion.com
Author: Akretion,Odoo Community Association (OCA)
Author-email: support@odoo-community.org
License: AGPL-3
Platform: UNKNOWN
Classifier: Programming Language :: Python
Classifier: Framework :: Odoo
Classifier: License :: OSI Approved :: GNU Affero General Public License v3
Requires-Python: ~=2.7
Requires-Dist: odoo8-addon-mis-builder
Requires-Dist: odoo (<9.0a,>=8.0a)
